Workbook

Sheet Sheet1
B2: Comparable Company Valuation | C2: (in crores)
C4: Market Data | I4: Financials | M4: Valuation
C5: Share | D5: Share | E5: Equity | G5: Enterprise
B6: Company | C6: Price | D6: Outstanding | E6: Value | F6: Net Debt | G6: Value | I6: Revenue | J6: EBITDA | K6: Net Income | M6: EV/Revenue | N6: EV/EBITDA | O6: P/E
B7: Hind. Unilever | C7: =Sheet2!D3 -> 2194.6 | D7: =Sheet2!G3 -> 234.96 | E7: =D7*C7 -> 515643.22 | F7: =Sheet2!F3-Sheet2!H3 -> -1770 | G7: =E7+F7 -> 513873.22 | I7: =Sheet2!E3 -> 64468 | J7: =Sheet2!J3+Sheet2!K3 -> 15790 | K7: =Sheet2!L3 -> 15059 | M7: =G7/I7 -> 7.9709812 | N7: =G7/J7 -> 32.544219 | O7: =E7/K7 -> 34.241531
B8: ITC | C8: =Sheet2!D4 -> 292.5 | D8: =Sheet2!G4 -> 1252.95 | E8: =D8*C8 -> 366487.88 | F8: =Sheet2!F4-Sheet2!H4 -> -609.73 | G8: =E8+F8 -> 365878.15 | I8: =Sheet2!E4 -> 78868.4 | J8: =Sheet2!J4+Sheet2!K4 -> 30120.79 | K8: =Sheet2!L4 -> 21018.15 | M8: =G8/I8 -> 4.6390968 | N8: =G8/J8 -> 12.14703 | O8: =E8/K8 -> 17.436733
B9: Nestle India | C9: =Sheet2!D5 -> 1414.8 | D9: =Sheet2!G5 -> 192.83 | E9: =D9*C9 -> 272815.88 | F9: =Sheet2!F5-Sheet2!H5 -> -896.71 | G9: =E9+F9 -> 271919.17 | I9: =Sheet2!E5 -> 23154.6 | J9: =Sheet2!J5+Sheet2!K5 -> 5342.42 | K9: =Sheet2!L5 -> 3544.6 | M9: =G9/I9 -> 11.743635 | N9: =G9/J9 -> 50.898127 | O9: =E9/K9 -> 76.966621
B10: Varun Beverages | C10: =Sheet2!D6 -> 529.5 | D10: =Sheet2!G6 -> 338.23 | E10: =D10*C10 -> 179092.79 | F10: =Sheet2!F6-Sheet2!H6 -> 509.69 | G10: =E10+F10 -> 179602.48 | I10: =Sheet2!E6 -> 22692.63 | J10: =Sheet2!J6+Sheet2!K6 -> 5672.75 | K10: =Sheet2!L6 -> 3209.4 | M10: =G10/I10 -> 7.9145729 | N10: =G10/J10 -> 31.660566 | O10: =E10/K10 -> 55.802575
B11: Britannia Inds. | C11: =Sheet2!D7 -> 5195 | D11: =Sheet2!G7 -> 24.09 | E11: =D11*C11 -> 125147.55 | F11: =Sheet2!F7-Sheet2!H7 -> 1027.84 | G11: =E11+F11 -> 126175.39 | I11: =Sheet2!E7 -> 19151.59 | J11: =Sheet2!J7+Sheet2!K7 -> 3738.37 | K11: =Sheet2!L7 -> 2537.01 | M11: =G11/I11 -> 6.5882462 | N11: =G11/J11 -> 33.751445 | O11: =E11/K11 -> 49.328757
B12: Tata Consumer | C12: =Sheet2!D8 -> 1111.5 | D12: =Sheet2!G8 -> 98.96 | E12: =D12*C12 -> 109994.04 | F12: =Sheet2!F8-Sheet2!H8 -> -600.98 | G12: =E12+F12 -> 109393.06 | I12: =Sheet2!E8 -> 20290.43 | J12: =Sheet2!J8+Sheet2!K8 -> 2928 | K12: =Sheet2!L8 -> 1546.8 | M12: =G12/I12 -> 5.3913623 | N12: =G12/J12 -> 37.361018 | O12: =E12/K12 -> 71.110706
B13: Marico | C13: =Sheet2!D9 -> 817.05 | D13: =Sheet2!G9 -> 129.84 | E13: =D13*C13 -> 106085.77 | F13: =Sheet2!F9-Sheet2!H9 -> 64 | G13: =E13+F13 -> 106149.77 | I13: =Sheet2!E9 -> 13611 | J13: =Sheet2!J9+Sheet2!K9 -> 2532 | K13: =Sheet2!L9 -> 1813 | M13: =G13/I13 -> 7.7988224 | N13: =G13/J13 -> 41.923291 | O13: =E13/K13 -> 58.513939
B14: Godrej Consumer | C14: =Sheet2!D10 -> 1000.6 | D14: =Sheet2!G10 -> 102.32 | E14: =D14*C14 -> 102381.39 | F14: =Sheet2!F10-Sheet2!H10 -> 3410.4 | G14: =E14+F14 -> 105791.79 | I14: =Sheet2!E10 -> 15177.9 | J14: =Sheet2!J10+Sheet2!K10 -> 3422.41 | K14: =Sheet2!L10 -> 1861.47 | M14: =G14/I14 -> 6.9701205 | N14: =G14/J14 -> 30.91149 | O14: =E14/K14 -> 55.000291
B15: United Spirits | C15: =Sheet2!D11 -> 1320.5 | D15: =Sheet2!G11 -> 72.74 | E15: =D15*C15 -> 96053.17 | F15: =Sheet2!F11-Sheet2!H11 -> -1564 | G15: =E15+F15 -> 94489.17 | I15: =Sheet2!E11 -> 12467 | J15: =Sheet2!J11+Sheet2!K11 -> 2757 | K15: =Sheet2!L11 -> 1838 | M15: =G15/I15 -> 7.5791425 | N15: =G15/J15 -> 34.272459 | O15: =E15/K15 -> 52.259614
B16: Dabur India | C16: =Sheet2!D12 -> 423.5 | D16: =Sheet2!G12 -> 177.4 | E16: =D16*C16 -> 75128.9 | F16: =Sheet2!F12-Sheet2!H12 -> 725.25 | G16: =E16+F16 -> 75854.15 | I16: =Sheet2!E12 -> 13192.57 | J16: =Sheet2!J12+Sheet2!K12 -> 3049.81 | K16: =Sheet2!L12 -> 1868.69 | M16: =G16/I16 -> 5.7497629 | N16: =G16/J16 -> 24.871763 | O16: =E16/K16 -> 40.204047
B18: High | M18: =MAX(M7:M16) -> 11.743635 | N18: =MAX(N7:N16) -> 50.898127 | O18: =MAX(O7:O16) -> 76.966621
B19: 75th percentile | M19: =QUARTILE(M7:M16,3) -> 7.8856353 | N19: =QUARTILE(N7:N16,3) -> 36.588878 | O19: =QUARTILE(O7:O16,3) -> 57.836098
B20: Average | M20: =AVERAGE(M7:M16) -> 7.2345743 | N20: =AVERAGE(N7:N16) -> 33.034141 | O20: =AVERAGE(O7:O16) -> 51.086481
B21: Median | M21: =MEDIAN(M7:M16) -> 7.2746315 | N21: =MEDIAN(N7:N16) -> 33.147832 | O21: =MEDIAN(O7:O16) -> 53.629952
B22: 25th percentile | M22: =QUARTILE(M7:M16,1) -> 5.9593838 | N22: =QUARTILE(N7:N16,1) -> 31.098759 | O22: =QUARTILE(O7:O16,1) -> 42.485224
B24: ITC Comparable Valuation | M24: EV/Revenue | N24: EV/EBITDA | O24: P/E
B25: Implied Enterprise Value | M25: =M21*I8 -> 573738.55 | N25: =N21*J8 -> 998438.89 | O25: =O27+O26 -> 1126592.7
B26: Net Debt | M26: =$F$8 -> -609.73 | N26: =$F$8 -> -609.73 | O26: =$F$8 -> -609.73
B27: Implied Market Value | M27: =M25-M26 -> 574348.28 | N27: =N25-N26 -> 999048.62 | O27: =O21*K8 -> 1127202.4
B28: Shares Outstanding | M28: =$D$8 -> 1252.95 | N28: =$D$8 -> 1252.95 | O28: =$D$8 -> 1252.95
B29: Implied value per share | M29: =M27/M28 -> 458.39681 | N29: =N27/N28 -> 797.35713 | O29: =O27/O28 -> 899.63876
M31: =IF($C$8>M29,"Overvalued","Undervalued") -> Undervalued | N31: =IF($C$8>N29,"Overvalued","Undervalued") -> Undervalued | O31: =IF($C$8>O29,"Overvalued","Undervalued") -> Undervalued

Sheet Sheet2
B2: S.No. | C2: Name | D2: CMP Rs. | E2: Sales Rs.Cr. | F2: Debt Rs.Cr. | G2: No. Eq. Shares Cr. | H2: Cash End Rs.Cr. | I2: EV Rs.Cr. | J2: EBIT 12M Rs.Cr. | K2: Dep 12M Rs.Cr. | L2: NP 12M Rs.Cr. | M2: Mar Cap Rs.Cr.
B3: 1 | C3: Hind. Unilever | D3: 2194.6 | E3: 64468 | F3: 1478 | G3: 234.96 | H3: 3248 | I3: 513871.3 | J3: 14457 | K3: 1333 | L3: 15059 | M3: 515641.3
B4: 2 | C4: ITC | D4: 292.5 | E4: 78868.4 | F4: 2399.06 | G4: 1252.95 | H4: 3008.79 | I4: 365877.22 | J4: 28410.26 | K4: 1710.53 | L4: 21018.15 | M4: 366486.95
B5: 3 | C5: Nestle India | D5: 1414.8 | E5: 23154.6 | F5: 444.16 | G5: 192.83 | H5: 1340.87 | I5: 271921.2 | J5: 4643.19 | K5: 699.23 | L5: 3544.6 | M5: 272817.91
B6: 4 | C6: Varun Beverages | D6: 529.5 | E6: 22692.63 | F6: 2508.18 | G6: 338.23 | H6: 1998.49 | I6: 179602.27 | J6: 4372.01 | K6: 1300.74 | L6: 3209.4 | M6: 179092.58
B7: 5 | C7: Britannia Inds. | D7: 5195 | E7: 19151.59 | F7: 1380.28 | G7: 24.09 | H7: 352.44 | I7: 126158.92 | J7: 3401.54 | K7: 336.83 | L7: 2537.01 | M7: 125131.08
B8: 6 | C8: Tata Consumer | D8: 1111.5 | E8: 20290.43 | F8: 2819.51 | G8: 98.96 | H8: 3420.49 | I8: 109398.09 | J8: 2301.32 | K8: 626.68 | L8: 1546.8 | M8: 109999.07
B9: 7 | C9: Marico | D9: 817.05 | E9: 13611 | F9: 557 | G9: 129.84 | H9: 493 | I9: 106147.76 | J9: 2330 | K9: 202 | L9: 1813 | M9: 106083.76
B10: 8 | C10: Godrej Consumer | D10: 1000.6 | E10: 15177.9 | F10: 4415.81 | G10: 102.32 | H10: 1005.41 | I10: 105796.25 | J10: 3154.88 | K10: 267.53 | L10: 1861.47 | M10: 102385.85
B11: 9 | C11: United Spirits | D11: 1320.5 | E11: 12467 | F11: 413 | G11: 72.74 | H11: 1977 | I11: 94482.68 | J11: 2468 | K11: 289 | L11: 1838 | M11: 96046.68
B12: 10 | C12: Dabur India | D12: 423.5 | E12: 13192.57 | F12: 1287.32 | G12: 177.4 | H12: 562.07 | I12: 75852.13 | J12: 2580.88 | K12: 468.93 | L12: 1868.69 | M12: 75126.88
